Engine/__init__.py
Engine_3d-0.6.dist-info/METADATA
Engine_3d-0.6.dist-info/WHEEL
Engine_3d-0.6.dist-info/top_level.txt
Engine_3d-0.6.dist-info/RECORD
