Metadata-Version: 2.1
Name: Engine-3d
Version: 0.6
Summary: Python 3d engine
Home-page: https://github.com/Xyon40k/PyEngine
Author: Alberto Rossani
Author-email: Alberto <rossani.alberto4@gmail.com>
License: MIT License
Project-URL: Homepage, https://github.com/Xyon40k/Engine
Keywords: engine,pygame
Classifier: License :: OSI Approved :: MIT License
Classifier: Programming Language :: Python
Classifier: Programming Language :: Python :: 3
Requires-Python: >=3.10
Requires-Dist: pygame (>=2.3.0)
